chat_cli/__init__.py
chat_cli/__main__.py
chat_cli/constants.py
chat_cli/conversation.py
chat_cli-0.3.5.dist-info/LICENSE
chat_cli-0.3.5.dist-info/METADATA
chat_cli-0.3.5.dist-info/WHEEL
chat_cli-0.3.5.dist-info/entry_points.txt
chat_cli-0.3.5.dist-info/RECORD
