Metadata-Version: 2.1
Name: chat-cli
Version: 0.3.5
Summary: Command line interaction with ChatGPT with chat history saved locally
Author: Robert Gingras
Requires-Python: >=3.8,<4.0
Classifier: Programming Language :: Python :: 3
Classifier: Programming Language :: Python :: 3.8
Classifier: Programming Language :: Python :: 3.9
Classifier: Programming Language :: Python :: 3.10
Classifier: Programming Language :: Python :: 3.11
Requires-Dist: argparse (>=1.4.0,<2.0.0)
Requires-Dist: openai (>=0.28.1,<0.29.0)
Requires-Dist: platformdirs (>=3.11.0,<4.0.0)
Requires-Dist: pyperclip (>=1.8.2,<2.0.0)
Requires-Dist: python-dotenv (>=1.0.0,<2.0.0)
Requires-Dist: tiktoken (>=0.5.1,<0.6.0)
Requires-Dist: typing-extensions (>=4.8.0,<5.0.0)
Requires-Dist: uuid6 (>=2023.5.2,<2024.0.0)
